pyoutlookdispatcher/__dispatcher.py
pyoutlookdispatcher/__init__.py
pyoutlookdispatcher-0.2.1.dist-info/WHEEL
pyoutlookdispatcher-0.2.1.dist-info/METADATA
pyoutlookdispatcher-0.2.1.dist-info/RECORD
