Metadata-Version: 2.1
Name: pyoutlookdispatcher
Version: 0.2.1
Summary: A Simple Email Dispatcher based on top of win32Api
Author: Rafael Tedesco
Author-email: dev.rafaeltedesco@gmail.com
Requires-Python: >=3.9,<4.0
Classifier: Programming Language :: Python :: 3
Classifier: Programming Language :: Python :: 3.10
Classifier: Programming Language :: Python :: 3.9
Requires-Dist: pywin32 (>=303,<304)
